sasa_db/crawler.py
sasa_db/db_rebuild.py
sasa_db/db_setup.py
sasa_db/exl_to_sql.py
sasa_db-0.1.dist-info/LICENSE
sasa_db-0.1.dist-info/METADATA
sasa_db-0.1.dist-info/WHEEL
sasa_db-0.1.dist-info/top_level.txt
sasa_db-0.1.dist-info/RECORD
