Metadata-Version: 2.1
Name: sasa-db
Version: 0.1
Summary: Utility to convert Excel tables to a sqlite database and access the data
Home-page: https://github.com/TimLucaTuran/sasa_db
Author: Tim Luca Turan
Author-email: timturan@web.de
License: MIT
Platform: UNKNOWN
Classifier: Programming Language :: Python :: 3
Classifier: License :: OSI Approved :: MIT License
Classifier: Operating System :: OS Independent
Requires-Dist: openpyxl
Requires-Dist: scipy
